custom_csv_tool/__init__.py
custom_csv_tool/tools.py
custom_csv_tool-0.1.0.dist-info/licenses/LICENSE
custom_csv_tool-0.1.0.dist-info/METADATA
custom_csv_tool-0.1.0.dist-info/WHEEL
custom_csv_tool-0.1.0.dist-info/top_level.txt
custom_csv_tool-0.1.0.dist-info/RECORD
