Metadata-Version: 2.4
Name: custom-csv-tool
Version: 0.1.0
Summary: Custom CrewAI tool for reading and analyzing CSVs from Azure Blob.
Author: Your Name
Requires-Python: >=3.7
License-File: LICENSE
Requires-Dist: pandas
Requires-Dist: numpy
Requires-Dist: pydantic
Requires-Dist: crewai
Requires-Dist: python-dotenv
Requires-Dist: azure-storage-blob
Dynamic: author
Dynamic: license-file
Dynamic: requires-dist
Dynamic: requires-python
Dynamic: summary
